Metadata-Version: 1.1
Name: pilbox
Version: 0.9.12
Summary: Pilbox is an image resizing application server built on the Tornado web framework using the Pillow Imaging Library
Home-page: https://github.com/agschwender/pilbox
Author: Adam Gschwender
Author-email: adam.gschwender@gmail.com
License: http://www.apache.org/licenses/LICENSE-2.0
Platform: UNKNOWN
Classifier: License :: OSI Approved :: Apache Software License
Classifier: Programming Language :: Python :: 2
Classifier: Programming Language :: Python :: 2.6
Classifier: Programming Language :: Python :: 2.7
Classifier: Programming Language :: Python :: 3
Classifier: Programming Language :: Python :: 3.2
Classifier: Programming Language :: Python :: 3.3
